robot_rock/__init__.py
robot_rock/api.py
robot_rock/cli.py
robot_rock/db.json
robot_rock-0.2.3.dist-info/entry_points.txt
robot_rock-0.2.3.dist-info/WHEEL
robot_rock-0.2.3.dist-info/METADATA
robot_rock-0.2.3.dist-info/RECORD
