Metadata-Version: 2.1
Name: robot-rock
Version: 0.2.3
Summary: 
Author: Oliver Josem
Author-email: omjosem@gmail.com
Requires-Python: >=3.7,<4.0
Classifier: Programming Language :: Python :: 3
Classifier: Programming Language :: Python :: 3.7
Classifier: Programming Language :: Python :: 3.8
Classifier: Programming Language :: Python :: 3.9
Requires-Dist: tinydb (>=4.5.0,<5.0.0)
Requires-Dist: typer[all] (>=0.3.2,<0.4.0)
